osmapi/OsmApi.py
osmapi/__init__.py
osmapi/dom.py
osmapi/errors.py
osmapi/http.py
osmapi/parser.py
osmapi/xmlbuilder.py
tests/__init__.py
tests/capabilities_test.py
tests/changeset_test.py
tests/conftest.py
tests/dom_test.py
tests/helper_test.py
tests/node_test.py
tests/notes_test.py
tests/osmapi_test.py
tests/relation_test.py
tests/way_test.py
osmapi-4.3.0.dist-info/LICENSE.txt
osmapi-4.3.0.dist-info/METADATA
osmapi-4.3.0.dist-info/WHEEL
osmapi-4.3.0.dist-info/top_level.txt
osmapi-4.3.0.dist-info/RECORD
