Metadata-Version: 2.1
Name: osmapi
Version: 4.3.0
Summary: Python wrapper for the OSM API
Home-page: https://github.com/metaodi/osmapi
Download-URL: https://github.com/metaodi/osmapi/archive/v4.3.0.zip
Author: Etienne Chové
Author-email: chove@crans.org
Maintainer: Stefan Oderbolz
Maintainer-email: odi@metaodi.ch
License: GPLv3
Keywords: openstreetmap,osm,api
Classifier: License :: OSI Approved :: GNU General Public License v3 (GPLv3)
Classifier: Intended Audience :: Developers
Classifier: Topic :: Scientific/Engineering :: GIS
Classifier: Topic :: Software Development :: Libraries
Classifier: Development Status :: 4 - Beta
Classifier: Programming Language :: Python :: 3
Classifier: Programming Language :: Python :: 3.8
Classifier: Programming Language :: Python :: 3.9
Classifier: Programming Language :: Python :: 3.10
Classifier: Programming Language :: Python :: 3.11
Requires-Python: >=3.8
License-File: LICENSE.txt
Requires-Dist: requests
